image_tiler/__init__.py
image_tiler/data_structures.py
image_tiler/tiler.py
image_tiler/utils.py
image_tiler-0.1.0.dist-info/METADATA
image_tiler-0.1.0.dist-info/WHEEL
image_tiler-0.1.0.dist-info/licenses/LICENSE
image_tiler-0.1.0.dist-info/RECORD
